LICENSE.txt
README.md
pyproject.toml
setup.cfg
setup.py
src/kindtool/__init__.py
src/kindtool/__main__.py
src/kindtool/cli.py
src/kindtool/cmddashboard.py
src/kindtool/cmddestroy.py
src/kindtool/cmdget.py
src/kindtool/cmdinit.py
src/kindtool/cmdshell.py
src/kindtool/cmdup.py
src/kindtool/kindfile.py
src/kindtool/runner.py
src/kindtool/templates.py
src/kindtool.egg-info/PKG-INFO
src/kindtool.egg-info/SOURCES.txt
src/kindtool.egg-info/dependency_links.txt
src/kindtool.egg-info/entry_points.txt
src/kindtool.egg-info/requires.txt
src/kindtool.egg-info/top_level.txt
src/kindtool/templates/dashboard-admin-user.yaml
src/kindtool/templates/dashboard-cluster-admin.yaml
src/kindtool/templates/kindfile.yaml
src/kindtool/templates/metallb-config.tpl.yaml
src/kindtool/templates/j2/config.j2.yaml
src/kindtool/templates/j2/controller.j2.yaml
src/kindtool/templates/j2/dashboard-install.j2.sh
src/kindtool/templates/j2/dot_gitignore.j2
src/kindtool/templates/j2/extramounts.j2.yaml
src/kindtool/templates/j2/ingress-install.j2.sh
src/kindtool/templates/j2/ingress-node.j2.yaml
src/kindtool/templates/j2/internal-registry-connect.j2.sh
src/kindtool/templates/j2/internal-registry-create.j2.sh
src/kindtool/templates/j2/internal-registry-delete.j2.sh
src/kindtool/templates/j2/internal-registry.j2.yaml
src/kindtool/templates/j2/metallb-install.j2.sh
src/kindtool/templates/j2/shell-delete.j2.sh
src/kindtool/templates/j2/shell-install.j2.sh
src/kindtool/templates/j2/update-metallb-ipaddresspool.j2.sh
src/kindtool/templates/j2/workers.j2.yaml