Metadata-Version: 2.1
Name: kindtool
Version: 0.0.4
Summary: Generator for kind k8s clusters
Home-page: https://github.com/egandro/kindtool
Author: Harald Fielker
Author-email: harald.fielker@gmail.com
License: UNKNOWN
Project-URL: Bug Reports, https://github.com/egandro/kindtool/issues
Project-URL: Source, https://github.com/egandro/kindtool/
Keywords: kind,k8s,generator,development
Platform: UNKNOWN
Classifier: Development Status :: 3 - Alpha
Classifier: Intended Audience :: Developers
Classifier: Topic :: Software Development :: Build Tools
Classifier: License :: OSI Approved :: MIT License
Classifier: Programming Language :: Python :: 3
Classifier: Programming Language :: Python :: 3.7
Classifier: Programming Language :: Python :: 3.8
Classifier: Programming Language :: Python :: 3.9
Classifier: Programming Language :: Python :: 3.10
Classifier: Programming Language :: Python :: 3.11
Classifier: Programming Language :: Python :: 3 :: Only
Requires-Python: >=3.7, <4
Provides-Extra: dev
Provides-Extra: test
